Modules/Phylogenetic.py
Modules/Prediction.py
Modules/__init__.py
plasmidperx-0.1.data/scripts/plasmidperm
plasmidperx-0.1.data/scripts/plasmidpermm
plasmidperx-0.1.data/scripts/plasmidpermmm
plasmidperx-0.1.data/scripts/plasmidperx
plasmidperx-0.1.dist-info/LICENSE
plasmidperx-0.1.dist-info/METADATA
plasmidperx-0.1.dist-info/WHEEL
plasmidperx-0.1.dist-info/top_level.txt
plasmidperx-0.1.dist-info/RECORD
